DIYA_Gesture/__init__.py
DIYA_Gesture/core.py
DIYA_Gesture/wheels.py
diya_gesture-1.2.0.dist-info/METADATA
diya_gesture-1.2.0.dist-info/WHEEL
diya_gesture-1.2.0.dist-info/top_level.txt
diya_gesture-1.2.0.dist-info/RECORD
