Metadata-Version: 2.4
Name: DIYA-Gesture
Version: 1.2.0
Summary: Control ESP32 robots using hand gestures (DIYA Robotics Edition)
Home-page: https://github.com/diyarobotics/DIYA_Gesture
Author: DIYA Robotics
Author-email: learn@diyaedulabs.com
Classifier: Programming Language :: Python :: 3
Classifier: Operating System :: OS Independent
Classifier: Topic :: Education
Classifier: Topic :: Scientific/Engineering :: Artificial Intelligence
Requires-Python: >=3.7
Requires-Dist: opencv-python
Requires-Dist: mediapipe
Requires-Dist: pyserial
Dynamic: author
Dynamic: author-email
Dynamic: classifier
Dynamic: description
Dynamic: description-content-type
Dynamic: home-page
Dynamic: requires-dist
Dynamic: requires-python
Dynamic: summary
